pylatent/__init__.py
pylatent-0.1.0.dist-info/METADATA
pylatent-0.1.0.dist-info/WHEEL
pylatent-0.1.0.dist-info/RECORD
