Metadata-Version: 2.1
Name: pylatent
Version: 0.1.0
Summary: Latent related utils and scripts.
Author: Mert Cobanov
Author-email: mertcobanov@gmail.com
Requires-Python: >=3.10,<4.0
Classifier: Programming Language :: Python :: 3
Classifier: Programming Language :: Python :: 3.10
Classifier: Programming Language :: Python :: 3.11
